macadamia/__init__.py
macadamia-0.2.0.dist-info/METADATA
macadamia-0.2.0.dist-info/WHEEL
macadamia-0.2.0.dist-info/top_level.txt
macadamia-0.2.0.dist-info/RECORD
